Workbook

Sheet Merit_Impact_Summary
A1: Merit Cycle Impact Summary
A2: Merit increases were allocated using a performance- and market-aligned matrix within a 3% budget. The cycle improved market competitiveness by reducing below-market pay positioning while maintaining internal equity and budget discipline.
A5: Market Alignment Impact
A6: Metric | B6: Pre-Merit | C6: Post-Merit
A8: Average Compa-Ratio | B8: =AVERAGE(Table1[Compa-Ratio]) -> 0.91135627 | C8: =AVERAGE(Table1[Post_Merit_Compa_Ratio]) -> 0.93937649
A9: % Below Market | B9: =COUNTIF(Table1[Market_Position],"Below Market")/COUNTA(Table1[Market_Position]) -> 0.295 | C9: =COUNTIF(Table1[Post_Merit_Position],"Below Market")/COUNTA(Table1[Post_Merit_Position]) -> 0.28
A11: Merit Distribution Insights
A12: Performance | B12: All Employees | C12: 5 | D12: 4 | E12: 3
A14: Average Merit Increase % | B14: =AVERAGEIF(Table1[Merit_Percent],">0") -> 0.036810345 | C14: =AVERAGEIFS(Table1[Merit_Percent],Table1[Performance_Rating],5) -> 0.051428571 | D14: =AVERAGEIFS(Table1[Merit_Percent],Table1[Performance_Rating],4) -> 0.041551724 | E14: =AVERAGEIFS(Table1[Merit_Percent],Table1[Performance_Rating],3) -> 0.030684211
A15: Average Merit $ Increase | B15: =AVERAGEIF(Table1[Merit_Amount],">0") -> 2859.1968 | C15: =AVERAGEIFS(Table1[Merit_Amount],Table1[Performance_Rating],5) -> 4021.8967 | D15: =AVERAGEIFS(Table1[Merit_Amount],Table1[Performance_Rating],4) -> 3228.8476 | E15: =AVERAGEIFS(Table1[Merit_Amount],Table1[Performance_Rating],3) -> 2376.4974
A16: Highest Merit Increase | B16: =MAX(Table1[Merit_Amount]) -> 5651.04 | C16: =_xlfn.MAXIFS(Table1[Merit_Amount],Table1[Performance_Rating],5) -> 5651.04 | D16: =_xlfn.MAXIFS(Table1[Merit_Amount],Table1[Performance_Rating],4) -> 4922.85 | E16: =_xlfn.MAXIFS(Table1[Merit_Amount],Table1[Performance_Rating],3) -> 3608.71
A18: Budget Summary Snapshot
A19: Merit Budget | B19: =Merit_Budget_Summary!B5 -> 465001.89
A20: Total Spend | B20: =Merit_Budget_Summary!B7 -> 497500.24
A21: Variance | B21: =Merit_Budget_Summary!B9 -> -32498.355

Sheet Merit_Budget_Summary
A1: Merit Budget Summary
A3: Total Payroll | B3: =SUM(Table1[base_salary]) -> 15500063
A5: Merit Budget (3%) | B5: =B3*0.03 -> 465001.89
A7: Total Merit Spend | B7: =SUM(Table1[Merit_Amount]) -> 497500.24
A9: Variance | B9: =B5-B7 -> -32498.355
A11: Scaling Factor | B11: =B5/B7 -> 0.93467671

Sheet Pay_Equity_Summary
A1: Purpose
A2: This analysis reviewed pay equity across similarly situated roles by comparing average pay and market positioning by gender within the same job title and level.
A4: Key Findings
A5: All roles showed low equity risk with pay differences within 5%.

Sheet Employee_Compensation_Analysis
N1: Market Positioning Analysis | U1: Pay Equity Analysis
A2: employee_id | B2: job_title | C2: job_family | D2: job_level | E2: exempt_status | F2: department | G2: location | H2: base_salary | I2: bonus_eligible | J2: Performance_Rating | K2: gender | L2: hire_date | M2: years_experience | N2: Market P25 | O2: Market Median | P2: Market P75 | Q2: Compa-Ratio | R2: Range_Penetration | S2: Market_Position | T2: Equity_Group | U2: Female Average Pay | V2: Male Average Pay | W2: Pay Gap % | X2: Equity | Y2: Merit_Eligible | Z2: Market_Col | AA2: Merit_Percent | AB2: Merit_Amount | AC2: New_Base_Salary | AD2: Post_Merit_Compa_Ratio | AE2: Post_Merit_Position
A3: 1000 | B3: Operations Manager | C3: Operations | D3: 4 | E3: Exempt | F3: Operations | G3: AL | H3: 99964 | I3: TRUE | J3: 3 | K3: Female | L3: 42836 | M3: 8 | N3: =VLOOKUP(B3,Market_Salary_Benchmarks!$A$1:$G$11,5,FALSE) -> 74720 | O3: =VLOOKUP(B3,Market_Salary_Benchmarks!$A$1:$G$11,6,FALSE) -> 106330 | P3: =VLOOKUP(B3,Market_Salary_Benchmarks!$A$1:$G$11,7,FALSE) -> 162780 | Q3: =H3/O3 -> 0.94012978 | R3: =(H3-N3)/(P3-N3) -> 0.28666818 | S3: =IF(H3 < N3, "Below Market", IF(H3 > P3, "Above Market", "At Market")) -> At Market | T3: =B3 & "-" & D3 -> Operations Manager-4 | U3: =AVERAGEIFS(H:H, K:K, "Female", B:B, B3, D:D, D3) -> 96094.111 | V3: =AVERAGEIFS(H:H, K:K, "Male", B:B, B3, D:D, D3) -> 95248.286 | W3: =(V3-U3)/V3 -> -0.0088802165 | X3: =IF(ABS(W3) >= 0.1, "High Risk", IF(ABS(W3) >= 0.05, "Moderate Risk", "Low Risk")) -> Low Risk | Y3: =IF(J3>=3,"Yes","No") -> Yes | Z3: =IF(TRIM(S3)="Below Market",1, IF(TRIM(S3)="At Market",2, IF(TRIM(S3)="Above Market",3,0))) -> 2 | AA3: {=IF($Y3<>"Yes",0,INDEX(Merit_Matrix!$B$2:$D$4,MATCH($J3,Merit_Matrix!$A$2:$A$4,0),Z3))} -> 0.03 | AB3: =H3*AA3 -> 2998.92 | AC3: =H3+AB3 -> 102962.92 | AD3: =AC3/O3 -> 0.96833368 | AE3: =IF(Table1[[#This Row],[New_Base_Salary]] < Table1[[#This Row],[Market P25]],"Below Market", IF(Table1[[#This Row],[New_Base_Salary]] > Table1[[#This Row],[Market P75]],"Above Market","At Market")) -> At Market
A4: 1001 | B4: IT Analyst | C4: IT | D4: 2 | E4: Exempt | F4: IT | G4: AL | H4: 61636 | I4: FALSE | J4: 4 | K4: Male | L4: 43139 | M4: 9 | N4: =VLOOKUP(B4,Market_Salary_Benchmarks!$A$1:$G$11,5,FALSE) -> 81130 | O4: =VLOOKUP(B4,Market_Salary_Benchmarks!$A$1:$G$11,6,FALSE) -> 103730 | P4: =VLOOKUP(B4,Market_Salary_Benchmarks!$A$1:$G$11,7,FALSE) -> 132670 | Q4: =H4/O4 -> 0.59419647 | R4: =(H4-N4)/(P4-N4) -> -0.3782305 | S4: =IF(H4 < N4, "Below Market", IF(H4 > P4, "Above Market", "At Market")) -> Below Market | T4: =B4 & "-" & D4 -> IT Analyst-2 | U4: =AVERAGEIFS(H:H, K:K, "Female", B:B, B4, D:D, D4) -> 55600.231 | V4: =AVERAGEIFS(H:H, K:K, "Male", B:B, B4, D:D, D4) -> 58468.727 | W4: =(V4-U4)/V4 -> 0.049060355 | X4: =IF(ABS(W4) >= 0.1, "High Risk", IF(ABS(W4) >= 0.05, "Moderate Risk", "Low Risk")) -> Low Risk | Y4: =IF(J4>=3,"Yes","No") -> Yes | Z4: =IF(TRIM(S4)="Below Market",1, IF(TRIM(S4)="At Market",2, IF(TRIM(S4)="Above Market",3,0))) -> 1 | AA4: {=IF($Y4<>"Yes",0,INDEX(Merit_Matrix!$B$2:$D$4,MATCH($J4,Merit_Matrix!$A$2:$A$4,0),Z4))} -> 0.05 | AB4: =H4*AA4 -> 3081.8 | AC4: =H4+AB4 -> 64717.8 | AD4: =AC4/O4 -> 0.6239063 | AE4: =IF(Table1[[#This Row],[New_Base_Salary]] < Table1[[#This Row],[Market P25]],"Below Market", IF(Table1[[#This Row],[New_Base_Salary]] > Table1[[#This Row],[Market P75]],"Above Market","At Market")) -> Below Market
A5: 1002 | B5: Operations Supervisor | C5: Operations | D5: 3 | E5: Non-Exempt | F5: Operations | G5: AL | H5: 75311 | I5: TRUE | J5: 2 | K5: Female | L5: 42391 | M5: 14 | N5: =VLOOKUP(B5,Market_Salary_Benchmarks!$A$1:$G$11,5,FALSE) -> 52500 | O5: =VLOOKUP(B5,Market_Salary_Benchmarks!$A$1:$G$11,6,FALSE) -> 67210 | P5: =VLOOKUP(B5,Market_Salary_Benchmarks!$A$1:$G$11,7,FALSE) -> 83970 | Q5: =H5/O5 -> 1.1205327 | R5: =(H5-N5)/(P5-N5) -> 0.72484906 | S5: =IF(H5 < N5, "Below Market", IF(H5 > P5, "Above Market", "At Market")) -> At Market | T5: =B5 & "-" & D5 -> Operations Supervisor-3 | U5: =AVERAGEIFS(H:H, K:K, "Female", B:B, B5, D:D, D5) -> 79072.214 | V5: =AVERAGEIFS(H:H, K:K, "Male", B:B, B5, D:D, D5) -> 76780.286 | W5: =(V5-U5)/V5 -> -0.029850482 | X5: =IF(ABS(W5) >= 0.1, "High Risk", IF(ABS(W5) >= 0.05, "Moderate Risk", "Low Risk")) -> Low Risk | Y5: =IF(J5>=3,"Yes","No") -> No | Z5: =IF(TRIM(S5)="Below Market",1, IF(TRIM(S5)="At Market",2, IF(TRIM(S5)="Above Market",3,0))) -> 2 | AA5: {=IF($Y5<>"Yes",0,INDEX(Merit_Matrix!$B$2:$D$4,MATCH($J5,Merit_Matrix!$A$2:$A$4,0),Z5))} -> 0 | AB5: =H5*AA5 -> 0 | AC5: =H5+AB5 -> 75311 | AD5: =AC5/O5 -> 1.1205327 | AE5: =IF(Table1[[#This Row],[New_Base_Salary]] < Table1[[#This Row],[Market P25]],"Below Market", IF(Table1[[#This Row],[New_Base_Salary]] > Table1[[#This Row],[Market P75]],"Above Market","At Market")) -> At Market
A6: 1003 | B6: Senior IT Analyst | C6: IT | D6: 3 | E6: Exempt | F6: IT | G6: AL | H6: 79274 | I6: TRUE | J6: 3 | K6: Female | L6: 45104 | M6: 4 | N6: =VLOOKUP(B6,Market_Salary_Benchmarks!$A$1:$G$11,5,FALSE) -> 103040 | O6: =VLOOKUP(B6,Market_Salary_Benchmarks!$A$1:$G$11,6,FALSE) -> 133500 | P6: =VLOOKUP(B6,Market_Salary_Benchmarks!$A$1:$G$11,7,FALSE) -> 171680 | Q6: =H6/O6 -> 0.59381273 | R6: =(H6-N6)/(P6-N6) -> -0.34624126 | S6: =IF(H6 < N6, "Below Market", IF(H6 > P6, "Above Market", "At Market")) -> Below Market | T6: =B6 & "-" & D6 -> Senior IT Analyst-3 | U6: =AVERAGEIFS(H:H, K:K, "Female", B:B, B6, D:D, D6) -> 78401.571 | V6: =AVERAGEIFS(H:H, K:K, "Male", B:B, B6, D:D, D6) -> 75875.125 | W6: =(V6-U6)/V6 -> -0.033297427 | X6: =IF(ABS(W6) >= 0.1, "High Risk", IF(ABS(W6) >= 0.05, "Moderate Risk", "Low Risk")) -> Low Risk | Y6: =IF(J6>=3,"Yes","No") -> Yes | Z6: =IF(TRIM(S6)="Below Market",1, IF(TRIM(S6)="At Market",2, IF(TRIM(S6)="Above Market",3,0))) -> 1 | AA6: {=IF($Y6<>"Yes",0,INDEX(Merit_Matrix!$B$2:$D$4,MATCH($J6,Merit_Matrix!$A$2:$A$4,0),Z6))} -> 0.035 | AB6: =H6*AA6 -> 2774.59 | AC6: =H6+AB6 -> 82048.59 | AD6: =AC6/O6 -> 0.61459618 | AE6: =IF(Table1[[#This Row],[New_Base_Salary]] < Table1[[#This Row],[Market P25]],"Below Market", IF(Table1[[#This Row],[New_Base_Salary]] > Table1[[#This Row],[Market P75]],"Above Market","At Market")) -> Below Market
A7: 1004 | B7: Operations Manager | C7: Operations | D7: 4 | E7: Exempt | F7: Operations | G7: AL | H7: 99394 | I7: TRUE | J7: 4 | K7: Male | L7: 44438 | M7: 10 | N7: =VLOOKUP(B7,Market_Salary_Benchmarks!$A$1:$G$11,5,FALSE) -> 74720 | O7: =VLOOKUP(B7,Market_Salary_Benchmarks!$A$1:$G$11,6,FALSE) -> 106330 | P7: =VLOOKUP(B7,Market_Salary_Benchmarks!$A$1:$G$11,7,FALSE) -> 162780 | Q7: =H7/O7 -> 0.93476912 | R7: =(H7-N7)/(P7-N7) -> 0.28019532 | S7: =IF(H7 < N7, "Below Market", IF(H7 > P7, "Above Market", "At Market")) -> At Market | T7: =B7 & "-" & D7 -> Operations Manager-4 | U7: =AVERAGEIFS(H:H, K:K, "Female", B:B, B7, D:D, D7) -> 96094.111 | V7: =AVERAGEIFS(H:H, K:K, "Male", B:B, B7, D:D, D7) -> 95248.286 | W7: =(V7-U7)/V7 -> -0.0088802165 | X7: =IF(ABS(W7) >= 0.1, "High Risk", IF(ABS(W7) >= 0.05, "Moderate Risk", "Low Risk")) -> Low Risk | Y7: =IF(J7>=3,"Yes","No") -> Yes | Z7: =IF(TRIM(S7)="Below Market",1, IF(TRIM(S7)="At Market",2, IF(TRIM(S7)="Above Market",3,0))) -> 2 | AA7: {=IF($Y7<>"Yes",0,INDEX(Merit_Matrix!$B$2:$D$4,MATCH($J7,Merit_Matrix!$A$2:$A$4,0),Z7))} -> 0.04 | AB7: =H7*AA7 -> 3975.76 | AC7: =H7+AB7 -> 103369.76 | AD7: =AC7/O7 -> 0.97215988 | AE7: =IF(Table1[[#This Row],[New_Base_Salary]] < Table1[[#This Row],[Market P25]],"Below Market", IF(Table1[[#This Row],[New_Base_Salary]] > Table1[[#This Row],[Market P75]],"Above Market","At Market")) -> At Market
A8: 1005 | B8: Operations Manager | C8: Operations | D8: 4 | E8: Exempt | F8: Operations | G8: AL | H8: 96792 | I8: TRUE | J8: 5 | K8: Female | L8: 44411 | M8: 10 | N8: =VLOOKUP(B8,Market_Salary_Benchmarks!$A$1:$G$11,5,FALSE) -> 74720 | O8: =VLOOKUP(B8,Market_Salary_Benchmarks!$A$1:$G$11,6,FALSE) -> 106330 | P8: =VLOOKUP(B8,Market_Salary_Benchmarks!$A$1:$G$11,7,FALSE) -> 162780 | Q8: =H8/O8 -> 0.91029813 | R8: =(H8-N8)/(P8-N8) -> 0.25064729 | S8: =IF(H8 < N8, "Below Market", IF(H8 > P8, "Above Market", "At Market")) -> At Market | T8: =B8 & "-" & D8 -> Operations Manager-4 | U8: =AVERAGEIFS(H:H, K:K, "Female", B:B, B8, D:D, D8) -> 96094.111 | V8: =AVERAGEIFS(H:H, K:K, "Male", B:B, B8, D:D, D8) -> 95248.286 | W8: =(V8-U8)/V8 -> -0.0088802165 | X8: =IF(ABS(W8) >= 0.1, "High Risk", IF(ABS(W8) >= 0.05, "Moderate Risk", "Low Risk")) -> Low Risk | Y8: =IF(J8>=3,"Yes","No") -> Yes | Z8: =IF(TRIM(S8)="Below Market",1, IF(TRIM(S8)="At Market",2, IF(TRIM(S8)="Above Market",3,0))) -> 2 | AA8: {=IF($Y8<>"Yes",0,INDEX(Merit_Matrix!$B$2:$D$4,MATCH($J8,Merit_Matrix!$A$2:$A$4,0),Z8))} -> 0.05 | AB8: =H8*AA8 -> 4839.6 | AC8: =H8+AB8 -> 101631.6 | AD8: =AC8/O8 -> 0.95581303 | AE8: =IF(Table1[[#This Row],[New_Base_Salary]] < Table1[[#This Row],[Market P25]],"Below Market", IF(Table1[[#This Row],[New_Base_Salary]] > Table1[[#This Row],[Market P75]],"Above Market","At Market")) -> At Market
A9: 1006 | B9: HR Manager | C9: HR | D9: 4 | E9: Exempt | F9: HR | G9: AL | H9: 103787 | I9: TRUE | J9: 3 | K9: Male | L9: 42404 | M9: 2 | N9: =VLOOKUP(B9,Market_Salary_Benchmarks!$A$1:$G$11,5,FALSE) -> 82620 | O9: =VLOOKUP(B9,Market_Salary_Benchmarks!$A$1:$G$11,6,FALSE) -> 110030 | P9: =VLOOKUP(B9,Market_Salary_Benchmarks!$A$1:$G$11,7,FALSE) -> 146810 | Q9: =H9/O9 -> 0.94326093 | R9: =(H9-N9)/(P9-N9) -> 0.32975541 | S9: =IF(H9 < N9, "Below Market", IF(H9 > P9, "Above Market", "At Market")) -> At Market | T9: =B9 & "-" & D9 -> HR Manager-4 | U9: =AVERAGEIFS(H:H, K:K, "Female", B:B, B9, D:D, D9) -> 97910.769 | V9: =AVERAGEIFS(H:H, K:K, "Male", B:B, B9, D:D, D9) -> 96300.667 | W9: =(V9-U9)/V9 -> -0.016719537 | X9: =IF(ABS(W9) >= 0.1, "High Risk", IF(ABS(W9) >= 0.05, "Moderate Risk", "Low Risk")) -> Low Risk | Y9: =IF(J9>=3,"Yes","No") -> Yes | Z9: =IF(TRIM(S9)="Below Market",1, IF(TRIM(S9)="At Market",2, IF(TRIM(S9)="Above Market",3,0))) -> 2 | AA9: {=IF($Y9<>"Yes",0,INDEX(Merit_Matrix!$B$2:$D$4,MATCH($J9,Merit_Matrix!$A$2:$A$4,0),Z9))} -> 0.03 | AB9: =H9*AA9 -> 3113.61 | AC9: =H9+AB9 -> 106900.61 | AD9: =AC9/O9 -> 0.97155876 | AE9: =IF(Table1[[#This Row],[New_Base_Salary]] < Table1[[#This Row],[Market P25]],"Below Market", IF(Table1[[#This Row],[New_Base_Salary]] > Table1[[#This Row],[Market P75]],"Above Market","At Market")) -> At Market
A10: 1007 | B10: Financial Analyst | C10: Finance | D10: 3 | E10: Exempt | F10: Finance | G10: AL | H10: 73943 | I10: TRUE | J10: 3 | K10: Female | L10: 43870 | M10: 3 | N10: =VLOOKUP(B10,Market_Salary_Benchmarks!$A$1:$G$11,5,FALSE) -> 49460 | O10: =VLOOKUP(B10,Market_Salary_Benchmarks!$A$1:$G$11,6,FALSE) -> 78370 | P10: =VLOOKUP(B10,Market_Salary_Benchmarks!$A$1:$G$11,7,FALSE) -> 104330 | Q10: =H10/O10 -> 0.94351155 | R10: =(H10-N10)/(P10-N10) -> 0.44620011 | S10: =IF(H10 < N10, "Below Market", IF(H10 > P10, "Above Market", "At Market")) -> At Market | T10: =B10 & "-" & D10 -> Financial Analyst-3 | U10: =AVERAGEIFS(H:H, K:K, "Female", B:B, B10, D:D, D10) -> 76962.636 | V10: =AVERAGEIFS(H:H, K:K, "Male", B:B, B10, D:D, D10) -> 77416 | W10: =(V10-U10)/V10 -> 0.0058562007 | X10: =IF(ABS(W10) >= 0.1, "High Risk", IF(ABS(W10) >= 0.05, "Moderate Risk", "Low Risk")) -> Low Risk | Y10: =IF(J10>=3,"Yes","No") -> Yes | Z10: =IF(TRIM(S10)="Below Market",1, IF(TRIM(S10)="At Market",2, IF(TRIM(S10)="Above Market",3,0))) -> 2 | AA10: {=IF($Y10<>"Yes",0,INDEX(Merit_Matrix!$B$2:$D$4,MATCH($J10,Merit_Matrix!$A$2:$A$4,0),Z10))} -> 0.03 | AB10: =H10*AA10 -> 2218.29 | AC10: =H10+AB10 -> 76161.29 | AD10: =AC10/O10 -> 0.97181689 | AE10: =IF(Table1[[#This Row],[New_Base_Salary]] < Table1[[#This Row],[Market P25]],"Below Market", IF(Table1[[#This Row],[New_Base_Salary]] > Table1[[#This Row],[Market P75]],"Above Market","At Market")) -> At Market
A11: 1008 | B11: HR Manager | C11: HR | D11: 4 | E11: Exempt | F11: HR | G11: AL | H11: 92297 | I11: TRUE | J11: 4 | K11: Female | L11: 43185 | M11: 9 | N11: =VLOOKUP(B11,Market_Salary_Benchmarks!$A$1:$G$11,5,FALSE) -> 82620 | O11: =VLOOKUP(B11,Market_Salary_Benchmarks!$A$1:$G$11,6,FALSE) -> 110030 | P11: =VLOOKUP(B11,Market_Salary_Benchmarks!$A$1:$G$11,7,FALSE) -> 146810 | Q11: =H11/O11 -> 0.83883486 | R11: =(H11-N11)/(P11-N11) -> 0.15075557 | S11: =IF(H11 < N11, "Below Market", IF(H11 > P11, "Above Market", "At Market")) -> At Market | T11: =B11 & "-" & D11 -> HR Manager-4 | U11: =AVERAGEIFS(H:H, K:K, "Female", B:B, B11, D:D, D11) -> 97910.769 | V11: =AVERAGEIFS(H:H, K:K, "Male", B:B, B11, D:D, D11) -> 96300.667 | W11: =(V11-U11)/V11 -> -0.016719537 | X11: =IF(ABS(W11) >= 0.1, "High Risk", IF(ABS(W11) >= 0.05, "Moderate Risk", "Low Risk")) -> Low Risk | Y11: =IF(J11>=3,"Yes","No") -> Yes | Z11: =IF(TRIM(S11)="Below Market",1, IF(TRIM(S11)="At Market",2, IF(TRIM(S11)="Above Market",3,0))) -> 2 | AA11: {=IF($Y11<>"Yes",0,INDEX(Merit_Matrix!$B$2:$D$4,MATCH($J11,Merit_Matrix!$A$2:$A$4,0),Z11))} -> 0.04 | AB11: =H11*AA11 -> 3691.88 | AC11: =H11+AB11 -> 95988.88 | AD11: =AC11/O11 -> 0.87238826 | AE11: =IF(Table1[[#This Row],[New_Base_Salary]] < Table1[[#This Row],[Market P25]],"Below Market", IF(Table1[[#This Row],[New_Base_Salary]] > Table1[[#This Row],[Market P75]],"Above Market","At Market")) -> At Market
A12: 1009 | B12: Operations Manager | C12: Operations | D12: 4 | E12: Exempt | F12: Operations | G12: AL | H12: 96529 | I12: TRUE | J12: 3 | K12: Female | L12: 44634 | M12: 13 | N12: =VLOOKUP(B12,Market_Salary_Benchmarks!$A$1:$G$11,5,FALSE) -> 74720 | O12: =VLOOKUP(B12,Market_Salary_Benchmarks!$A$1:$G$11,6,FALSE) -> 106330 | P12: =VLOOKUP(B12,Market_Salary_Benchmarks!$A$1:$G$11,7,FALSE) -> 162780 | Q12: =H12/O12 -> 0.9078247 | R12: =(H12-N12)/(P12-N12) -> 0.24766069 | S12: =IF(H12 < N12, "Below Market", IF(H12 > P12, "Above Market", "At Market")) -> At Market | T12: =B12 & "-" & D12 -> Operations Manager-4 | U12: =AVERAGEIFS(H:H, K:K, "Female", B:B, B12, D:D, D12) -> 96094.111 | V12: =AVERAGEIFS(H:H, K:K, "Male", B:B, B12, D:D, D12) -> 95248.286 | W12: =(V12-U12)/V12 -> -0.0088802165 | X12: =IF(ABS(W12) >= 0.1, "High Risk", IF(ABS(W12) >= 0.05, "Moderate Risk", "Low Risk")) -> Low Risk | Y12: =IF(J12>=3,"Yes","No") -> Yes | Z12: =IF(TRIM(S12)="Below Market",1, IF(TRIM(S12)="At Market",2, IF(TRIM(S12)="Above Market",3,0))) -> 2 | AA12: {=IF($Y12<>"Yes",0,INDEX(Merit_Matrix!$B$2:$D$4,MATCH($J12,Merit_Matrix!$A$2:$A$4,0),Z12))} -> 0.03 | AB12: =H12*AA12 -> 2895.87 | AC12: =H12+AB12 -> 99424.87 | AD12: =AC12/O12 -> 0.93505944 | AE12: =IF(Table1[[#This Row],[New_Base_Salary]] < Table1[[#This Row],[Market P25]],"Below Market", IF(Table1[[#This Row],[New_Base_Salary]] > Table1[[#This Row],[Market P75]],"Above Market","At Market")) -> At Market
A13: 1010 | B13: Senior IT Analyst | C13: IT | D13: 3 | E13: Exempt | F13: IT | G13: AL | H13: 72062 | I13: TRUE | J13: 1 | K13: Male | L13: 43737 | M13: 2 | N13: =VLOOKUP(B13,Market_Salary_Benchmarks!$A$1:$G$11,5,FALSE) -> 103040 | O13: =VLOOKUP(B13,Market_Salary_Benchmarks!$A$1:$G$11,6,FALSE) -> 133500 | P13: =VLOOKUP(B13,Market_Salary_Benchmarks!$A$1:$G$11,7,FALSE) -> 171680 | Q13: =H13/O13 -> 0.53979026 | R13: =(H13-N13)/(P13-N13) -> -0.45131119 | S13: =IF(H13 < N13, "Below Market", IF(H13 > P13, "Above Market", "At Market")) -> Below Market | T13: =B13 & "-" & D13 -> Senior IT Analyst-3 | U13: =AVERAGEIFS(H:H, K:K, "Female", B:B, B13, D:D, D13) -> 78401.571 | V13: =AVERAGEIFS(H:H, K:K, "Male", B:B, B13, D:D, D13) -> 75875.125 | W13: =(V13-U13)/V13 -> -0.033297427 | X13: =IF(ABS(W13) >= 0.1, "High Risk", IF(ABS(W13) >= 0.05, "Moderate Risk", "Low Risk")) -> Low Risk | Y13: =IF(J13>=3,"Yes","No") -> No | Z13: =IF(TRIM(S13)="Below Market",1, IF(TRIM(S13)="At Market",2, IF(TRIM(S13)="Above Market",3,0))) -> 1 | AA13: {=IF($Y13<>"Yes",0,INDEX(Merit_Matrix!$B$2:$D$4,MATCH($J13,Merit_Matrix!$A$2:$A$4,0),Z13))} -> 0 | AB13: =H13*AA13 -> 0 | AC13: =H13+AB13 -> 72062 | AD13: =AC13/O13 -> 0.53979026 | AE13: =IF(Table1[[#This Row],[New_Base_Salary]] < Table1[[#This Row],[Market P25]],"Below Market", IF(Table1[[#This Row],[New_Base_Salary]] > Table1[[#This Row],[Market P75]],"Above Market","At Market")) -> Below Market
A14: 1011 | B14: IT Analyst | C14: IT | D14: 2 | E14: Exempt | F14: IT | G14: AL | H14: 59687 | I14: FALSE | J14: 4 | K14: Male | L14: 44706 | M14: 12 | N14: =VLOOKUP(B14,Market_Salary_Benchmarks!$A$1:$G$11,5,FALSE) -> 81130 | O14: =VLOOKUP(B14,Market_Salary_Benchmarks!$A$1:$G$11,6,FALSE) -> 103730 | P14: =VLOOKUP(B14,Market_Salary_Benchmarks!$A$1:$G$11,7,FALSE) -> 132670 | Q14: =H14/O14 -> 0.57540731 | R14: =(H14-N14)/(P14-N14) -> -0.41604579 | S14: =IF(H14 < N14, "Below Market", IF(H14 > P14, "Above Market", "At Market")) -> Below Market | T14: =B14 & "-" & D14 -> IT Analyst-2 | U14: =AVERAGEIFS(H:H, K:K, "Female", B:B, B14, D:D, D14) -> 55600.231 | V14: =AVERAGEIFS(H:H, K:K, "Male", B:B, B14, D:D, D14) -> 58468.727 | W14: =(V14-U14)/V14 -> 0.049060355 | X14: =IF(ABS(W14) >= 0.1, "High Risk", IF(ABS(W14) >= 0.05, "Moderate Risk", "Low Risk")) -> Low Risk | Y14: =IF(J14>=3,"Yes","No") -> Yes | Z14: =IF(TRIM(S14)="Below Market",1, IF(TRIM(S14)="At Market",2, IF(TRIM(S14)="Above Market",3,0))) -> 1 | AA14: {=IF($Y14<>"Yes",0,INDEX(Merit_Matrix!$B$2:$D$4,MATCH($J14,Merit_Matrix!$A$2:$A$4,0),Z14))} -> 0.05 | AB14: =H14*AA14 -> 2984.35 | AC14: =H14+AB14 -> 62671.35 | AD14: =AC14/O14 -> 0.60417767 | AE14: =IF(Table1[[#This Row],[New_Base_Salary]] < Table1[[#This Row],[Market P25]],"Below Market", IF(Table1[[#This Row],[New_Base_Salary]] > Table1[[#This Row],[Market P75]],"Above Market","At Market")) -> Below Market
... A202: 1199 | B202: Senior Financial Analyst | C202: Finance | D202: 4 | E202: Exempt | F202: Finance | G202: AL | H202: 93233 | I202: TRUE | J202: 3 | K202: Female | L202: 42687 | M202: 14 | N202: =VLOOKUP(B202,Market_Salary_Benchmarks!$A$1:$G$11,5,FALSE) -> 105000 | O202: =VLOOKUP(B202,Market_Salary_Benchmarks!$A$1:$G$11,6,FALSE) -> 138040 | P202: =VLOOKUP(B202,Market_Salary_Benchmarks!$A$1:$G$11,7,FALSE) -> 179950 | Q202: =H202/O202 -> 0.67540568 | R202: =(H202-N202)/(P202-N202) -> -0.156998 | S202: =IF(H202 < N202, "Below Market", IF(H202 > P202, "Above Market", "At Market")) -> Below Market | T202: =B202 & "-" & D202 -> Senior Financial Analyst-4 | U202: =AVERAGEIFS(H:H, K:K, "Female", B:B, B202, D:D, D202) -> 94329.75 | V202: =AVERAGEIFS(H:H, K:K, "Male", B:B, B202, D:D, D202) -> 94897.167 | W202: =(V202-U202)/V202 -> 0.0059792793 | X202: =IF(ABS(W202) >= 0.1, "High Risk", IF(ABS(W202) >= 0.05, "Moderate Risk", "Low Risk")) -> Low Risk | Y202: =IF(J202>=3,"Yes","No") -> Yes | Z202: =IF(TRIM(S202)="Below Market",1, IF(TRIM(S202)="At Market",2, IF(TRIM(S202)="Above Market",3,0))) -> 1 | AA202: {=IF($Y202<>"Yes",0,INDEX(Merit_Matrix!$B$2:$D$4,MATCH($J202,Merit_Matrix!$A$2:$A$4,0),Z202))} -> 0.035 | AB202: =H202*AA202 -> 3263.155 | AC202: =H202+AB202 -> 96496.155 | AD202: =AC202/O202 -> 0.69904488 | AE202: =IF(Table1[[#This Row],[New_Base_Salary]] < Table1[[#This Row],[Market P25]],"Below Market", IF(Table1[[#This Row],[New_Base_Salary]] > Table1[[#This Row],[Market P75]],"Above Market","At Market")) -> Below Market

Sheet Market_Salary_Benchmarks
A1: Job Title | B1: Level | C1: External Benchmark | D1: Source | E1: Market P25 | F1: Market Median | G1: Market P75
A2: HR Analyst | B2: 2 | C2: Human Resources Specialists | D2: BLS OEWS | E2: 48890 | F2: 62770 | G2: 82990
A3: Payroll Specialist | B3: 2 | C3: Payroll and Timekeeping Clerks | D3: BLS OEWS | E3: 37930 | F3: 45470 | G3: 54160
A4: IT Analyst | B4: 2 | C4: Computer Systems Analysts | D4: BLS OEWS | E4: 81130 | F4: 103730 | G4: 132670
A5: Compensation Analyst | B5: 3 | C5: Compensation, Benefits, and Job Analysis Specialists | D5: BLS OEWS | E5: 50970 | F5: 56720 | G5: 75360
A6: Financial Analyst | B6: 3 | C6: Financial and Investment Analysts | D6: BLS OEWS | E6: 49460 | F6: 78370 | G6: 104330
A7: Senior IT Analyst | B7: 3 | C7: Computer and Information Systems Managers | D7: BLS OEWS | E7: 103040 | F7: 133500 | G7: 171680
A8: Operations Supervisor | B8: 3 | C8: First-Line Supervisors of Production and Operating Workers | D8: BLS OEWS | E8: 52500 | F8: 67210 | G8: 83970
A9: HR Manager | B9: 4 | C9: Human Resources Managers | D9: BLS OEWS | E9: 82620 | F9: 110030 | G9: 146810
A10: Senior Financial Analyst | B10: 4 | C10: Financial Managers | D10: BLS OEWS | E10: 105000 | F10: 138040 | G10: 179950
A11: Operations Manager | B11: 4 | C11: General and Operations Managers | D11: BLS OEWS | E11: 74720 | F11: 106330 | G11: 162780

Sheet Job_Matching
A1: Internal Job Title | B1: Job Family | C1: Level | D1: External Benchmark Title | E1: Source | F1: Matching Rationale | G1: Confidence | H1: Internal Job Title | I1: Job Family | J1: Level | K1: External Benchmark Title | L1: Source | M1: Matching Rationale | N1: Confidence | O1: Internal Job Title | P1: Job Family | Q1: Level | R1: External Benchmark Title | S1: Source | T1: Matching Rationale | U1: Confidence | V1: Internal Job Title | W1: Job Family | X1: Level | Y1: External Benchmark Title | Z1: Source | AA1: Matching Rationale | AB1: Confidence
A2: HR Analyst | B2: HR | C2: 2 | D2: Human Resources Specialists | E2: BLS OEWS | F2: Support-level HR work including reporting and administration | G2: High | H2: Financial Analyst | I2: Finance | J2: 3 | K2: Financial and Investment Analysts | L2: BLS OEWS | M2: Financial modeling, forecasting, and business analysis | N2: High | O2: Operations Supervisor | P2: Operations | Q2: 3 | R2: First-Line Supervisors of Production and Operating Workers | S2: BLS OEWS | T2: Frontline supervision and scheduling responsibilities | U2: High | V2: IT Analyst | W2: IT | X2: 2 | Y2: Computer Systems Analysts | Z2: BLS OEWS | AA2: Technical support and issue resolution | AB2: High
A3: Payroll Specialist | B3: HR | C3: 2 | D3: Payroll and Timekeeping Clerks | E3: BLS OEWS | F3: Transactional payroll processing and compliance tasks | G3: High | H3: Senior Financial Analyst | I3: Finance | J3: 4 | K3: Financial Managers | L3: BLS OEWS | M3: Leads financial planning and advises leadership | N3: Medium | O3: Operations Manager | P3: Operations | Q3: 4 | R3: General and Operations Managers | S3: BLS OEWS | T3: Owns operational strategy and performance | U3: High | V3: Senior IT Analyst | W3: IT | X3: 3 | Y3: Computer and Information Systems Managers | Z3: BLS OEWS | AA3: System ownership and advanced problem-solving | AB3: High
A4: Compensation Analyst | B4: HR | C4: 3 | D4: Compensation, Benefits, and Job Analysis Specialists | E4: BLS OEWS | F4: Compensation analysis, market pricing, and advisory work | G4: High
A5: HR Manager | B5: HR | C5: 4 | D5: Human Resources Managers | E5: BLS OEWS | F5: Strategic HR leadership and people management | G5: High

Sheet JobArchitecture_LevelingRation
D1: HR Family | F1: Finance Family | H1: Operations Family | J1: IT Family
A2: Level | B2: Title Pattern | C2: Core Characteristics | D2: Job Title | E2: Justification | F2: Job Title | G2: Justification | H2: Job Title | I2: Justification | J2: Job Title | K2: Justification
A3: Level 2 | B3: Analyst / Specialist | C3: Executes defined tasks, limited autonomy, works under guidance | D3: (1) HR Analyst (2) Payroll Specialist | E3: (1) Supports HR programs, executes reporting and admin tasks; (2) Transactional, compliance-focused, limited decision authority | J3: IT Analyst | K3: Provides technical support and executes defined tasks under established procedures
A4: Level 3 | B4: Senior / Lead Analyst | C4: Independent contributor or frontline supervisor; exercises independent judgment within defined frameworks; role expertise; may oversee staff without owning strategy or budgets | D4: Compensation Analyst | E4: Owns compensation analysis, advises HR leadership | F4: Financial Analyst | G4: Independent analysis, forecasting, business partnering | H4: Operations Supervisor | I4: Supervises frontline staff, manages schedules | J4: Senior IT Analyst | K4: System ownership, advanced problem-solving
A5: Level 4 | B5: Manager | C5: Manages people or functions, sets strategy, owns outcomes | D5: HR Manager | E5: Leads HR strategy, manages staff, accountable for outcomes | F5: Senior Financial Analyst | G5: Leads financial planning, advises leadership | H5: Operations Manager | I5: Owns operational performance and strategy

Sheet Market_Data_Methodology
A1: Pay Range Rules | C1: Data Sources | E1: Job Matching Approach | H1: Georgraphic Scope
A2: Range Component | B2: Value | C2: Category | D2: Description | E2: Internal Job Title | F2: External Benchmark | G2: Rationale | H2: Item | I2: Value
A3: Minimum | B3: Market P25 | C3: Primary Wage Source | D3: BLS Occupational Employment and Wage Statistics (OEWS) | E3: Compensation Analyst | F3: Compensation, Benefits, and Job Analysis Specialists | G3: Role scope and analytical responsibilities | H3: Geography | I3: Alabama
A4: Midpoint | B4: Market Median | C4: Job Matching Reference | D4: O*NET Online occupational descriptions | E4: HR Analyst | F4: Human Resources Specialists | G4: Support-level HR functions
A5: Maximum | B5: Market P75 | C5: Survey Simulation | D5: Percentiles aligned to typical compensation survey outputs | E5: Operations Supervisor | F5: First-Line Supervisors of Production and Operating Workers | G5: Frontline supervision, scheduling
E6: Payroll Specialist | F6: Payroll and Timekeeping Clerks | G6: Verify attendance, hours worked, and pay adjustments, and post information onto designated records. Process and issue employee paychecks and statements of earnings and deductions.
E7: IT Analyst | F7: Computer Systems Analysts | G7: Test, maintain, and monitor computer programs and systems, including coordinating the installation of computer programs and systems.
E8: Financial Analyst | F8: Financial and Investment Analysts | G8: Analyze financial or operational performance
E9: Senior IT Analyst | F9: Computer and Information Systems Managers | G9: Direct daily operations of department, analyzing workflow, establishing priorities, developing standards and setting deadlines.
E10: HR Manager | F10: Human Resources Managers | G10: Supervise employees, hire personnel and manage human resources activities
E11: Senior Financial Analyst | F11: Financial Managers | G11: Evaluate financial reporting systems, accounting or collection procedures, or investment activities and make recommendations for changes to procedures, operating systems, budgets, or other financial control functions.
E12: Operations Manager | F12: General and Operations Managers | G12: Direct or coordinate financial or budget activities to fund operations, maximize investments, or increase efficiency.

Sheet Merit_Matrix
A1: Performance Rating | B1: Below Market | C1: At Market | D1: Above Market
A2: 5 | B2: 0.06 | C2: 0.05 | D2: 0.04
A3: 4 | B3: 0.05 | C3: 0.04 | D3: 0.03
A4: 3 | B4: 0.035 | C4: 0.03 | D4: 0.02
